titles_art/__init__.py
titles_art/abecedario_ascii.py
titles_art/main.py
TitlesArt-1.1.0.dist-info/METADATA
TitlesArt-1.1.0.dist-info/WHEEL
TitlesArt-1.1.0.dist-info/top_level.txt
TitlesArt-1.1.0.dist-info/RECORD
