Metadata-Version: 2.1
Name: TitlesArt
Version: 1.1.0
Summary: Create titles for command-line tools easily.
Home-page: https://github.com/PACHOOF/TitlesArt.git
Author: Pachi
Author-email: pachoof345@gmail.com
Classifier: Programming Language :: Python :: 3
Classifier: License :: OSI Approved :: MIT License
Classifier: Operating System :: OS Independent
Requires-Python: >=3.6
